dojocommons/__init__.py
dojocommons/py.typed
dojocommons/controller/__init__.py
dojocommons/controller/base_controller.py
dojocommons/exception/__init__.py
dojocommons/exception/business_exception.py
dojocommons/model/__init__.py
dojocommons/model/app_configuration.py
dojocommons/model/base_event.py
dojocommons/model/base_resource.py
dojocommons/model/response.py
dojocommons/repository/__init__.py
dojocommons/repository/base_repository.py
dojocommons/service/__init__.py
dojocommons/service/base_service.py
dojocommons/service/db_service.py
dojocommons/util/__init__.py
dojocommons/util/model_util.py
dojocommons-1.2.7.dist-info/licenses/LICENSE
dojocommons-1.2.7.dist-info/METADATA
dojocommons-1.2.7.dist-info/WHEEL
dojocommons-1.2.7.dist-info/top_level.txt
dojocommons-1.2.7.dist-info/RECORD
