Metadata-Version: 2.4
Name: dojocommons
Version: 1.2.7
Summary: Classes comuns para o projeto Dojo Management.
Author-email: Rodrigo Gregori <rodrigo.gregori@gmail.com>
License: MIT
Requires-Python: >=3.11
License-File: LICENSE
Requires-Dist: boto3~=1.37.18
Requires-Dist: duckdb~=1.2.1
Requires-Dist: pydantic~=2.10.6
Requires-Dist: pydantic-settings~=2.8.1
Provides-Extra: dev
Requires-Dist: coverage>=7.8.2; extra == "dev"
Dynamic: license-file
